	[
		{"id":1, "name":"hamsadhwani", "lang":"hindi", "artist":"abc", "album":"xyz", "rating":10, "link": ""},
		{"id":2, "name":"hamsadhwani", "lang":"hindi", "artist":"abc", "album":"xyz", "rating":10, "link": ""},
		{"id":3, "name":"hamsadhwani", "lang":"hindi", "artist":"abc", "album":"This is a long name for an album", "rating":10, "link": ""},
		{"id":4, "name":"hamsadhwani", "lang":"hindi", "artist":"abc", "album":"xyz", "rating":10, "link": ""},
		{"id":5, "name":"hamsadhwani", "lang":"hindi", "artist":"abc", "album":"xyz", "rating":10, "link": ""},
		{"id":6, "name":"kalyani", "lang":"hindi", "artist":"abc", "album":"xyz", "rating":10, "link": ""},
		{"id":7, "name":"hamsadhwani", "lang":"hindi", "artist":"abc", "album":"xyz", "rating":10, "link": ""},
		{"id":8, "name":"hamsadhwani", "lang":"hindi", "artist":"abc", "album":"xyz", "rating":10, "link": ""},
		{"id":9, "name":"hamsadhwani", "lang":"hindi", "artist":"abc", "album":"xyz", "rating":10, "link": ""},
		{"id":10, "name":"hamsadhwani", "lang":"hindi", "artist":"abc", "album":"xyz", "rating":10, "link": ""},
		{"id":11, "name":"hamsadhwani", "lang":"hindi", "artist":"Ustad Amjad Ali Khan", "album":"xyz", "rating":10, "link": ""},
		{"id":12, "name":"bhairavi", "lang":"hindi", "artist":"abc", "album":"xyz", "rating":10, "link": ""},
		{"id":13, "name":"hamsadhwani", "lang":"hindi", "artist":"abc", "album":"xyz", "rating":10, "link": ""},
		{"id":14, "name":"hamsadhwani", "lang":"hindi", "artist":"abc", "album":"xyz", "rating":10, "link": ""},
		{"id":15, "name":"hamsadhwani", "lang":"hindi", "artist":"abc", "album":"xyz", "rating":10, "link": ""},
		{"id":16, "name":"hamsadhwani", "lang":"hindi", "artist":"abc", "album":"xyz", "rating":10, "link": ""},
		{"id":17, "name":"hamsadhwani", "lang":"hindi", "artist":"abc", "album":"xyz", "rating":10, "link": ""},
		{"id":18, "name":"hamsadhwani", "lang":"hindi", "artist":"abc", "album":"xyz", "rating":10, "link": ""},
		{"id":19, "name":"malhar", "lang":"hindi", "artist":"abc", "album":"xyz", "rating":10, "link": ""},
		{"id":20, "name":"hamsadhwani", "lang":"hindi", "artist":"abc", "album":"xyz", "rating":10, "link": ""},
		{"id":21, "name":"hamsadhwani", "lang":"hindi", "artist":"abc", "album":"xyz", "rating":10, "link": ""},
		{"id":22, "name":"hamsadhwani", "lang":"telugu", "artist":"abc", "album":"xyz", "rating":10, "link": ""},
		{"id":23, "name":"kambhoji", "lang":"hindi", "artist":"abc", "album":"xyz", "rating":10, "link": ""},
		{"id":24, "name":"hamsadhwani", "lang":"hindi", "artist":"abc", "album":"An extra extra extra extra loooong name for testing", "rating":10, "link": ""},
		{"id":25, "name":"hamsadhwani", "lang":"hindi", "artist":"abc", "album":"xyz", "rating":10, "link": ""},
		{"id":26, "name":"hamsadhwani", "lang":"kannada", "artist":"abc", "album":"xyz", "rating":10, "link": ""},
		{"id":27, "name":"hamsadhwani", "lang":"hindi", "artist":"abc", "album":"xyz", "rating":10, "link": ""},
		{"id":28, "name":"hamsadhwani", "lang":"kannada", "artist":"abc", "album":"xyz", "rating":10, "link": ""},
		{"id":29, "name":"kambhoji", "lang":"hindi", "artist":"abc", "album":"xyz", "rating":10, "link": ""},
		{"id":30, "name":"hamsadhwani", "lang":"hindi", "artist":"abc", "album":"xyz", "rating":10, "link": ""},
		{"id":31, "name":"hamsadhwani", "lang":"kannada", "artist":"abc", "album":"xyz", "rating":10, "link": ""},
		{"id":32, "name":"hamsadhwani", "lang":"hindi", "artist":"abc", "album":"xyz", "rating":10, "link": ""},
		{"id":33, "name":"kalyani", "lang":"hindi", "artist":"abc", "album":"xyz", "rating":10, "link": ""},
		{"id":34, "name":"hamsadhwani", "lang":"hindi", "artist":"abc", "album":"xyz", "rating":10, "link": ""},
		{"id":35, "name":"hamsadhwani", "lang":"hindi", "artist":"abc", "album":"xyz", "rating":10, "link": ""},
		{"id":36, "name":"hamsadhwani", "lang":"hindi", "artist":"abc", "album":"xyz", "rating":10, "link": ""},
		{"id":37, "name":"hamsadhwani", "lang":"hindi", "artist":"abc", "album":"xyz", "rating":10, "link": ""},
		{"id":38, "name":"hamsadhwani", "lang":"hindi", "artist":"abc", "album":"xyz", "rating":10, "link": ""}
	]